cakemail/__init__.py
cakemail/account.py
cakemail/action.py
cakemail/api.py
cakemail/automation.py
cakemail/campaign.py
cakemail/campaign_blueprint.py
cakemail/contact.py
cakemail/custom_attribute.py
cakemail/domain.py
cakemail/form.py
cakemail/list.py
cakemail/log.py
cakemail/logo.py
cakemail/models.py
cakemail/report.py
cakemail/response.py
cakemail/segment.py
cakemail/sender.py
cakemail/sub_account.py
cakemail/suppressed_email.py
cakemail/system_email.py
cakemail/task.py
cakemail/template.py
cakemail/token.py
cakemail/transactional_email.py
cakemail/user.py
cakemail/webhook.py
cakemail/workflow.py
cakemail/workflow_blueprint.py
cakemail/wrapper.py
cakemail-1.12.14.dist-info/METADATA
cakemail-1.12.14.dist-info/WHEEL
cakemail-1.12.14.dist-info/top_level.txt
cakemail-1.12.14.dist-info/RECORD
