Metadata-Version: 2.1
Name: cakemail
Version: 1.12.14
Summary: Cakemail Next-gen API client
Home-page: https://github.com/cakemail/cakemail-python
License: MIT
Platform: UNKNOWN
Requires-Python: >=3.6
Requires-Dist: six
Requires-Dist: urllib3
Requires-Dist: certifi
Requires-Dist: python-dateutil
Requires-Dist: cakemail-openapi (==1.12.14)
